vwap/__init__.py
vwap/data.py
vwap/portfolio.py
vwap/signal_figure.py
vwap/signal_gen.py
vwap/test.py
VWAP-1.0.4.dist-info/LICENSE.txt.txt
VWAP-1.0.4.dist-info/METADATA
VWAP-1.0.4.dist-info/WHEEL
VWAP-1.0.4.dist-info/top_level.txt
VWAP-1.0.4.dist-info/RECORD
