Metadata-Version: 2.1
Name: VWAP
Version: 1.0.4
Summary: Buy and Sell signals using VWAP-based trading algorithm
Home-page: UNKNOWN
Author: Saad Lahrichi
Author-email: sl636@duke.edu
License: MIT
Platform: UNKNOWN
Classifier: License :: OSI Approved :: MIT License
Classifier: Programming Language :: Python :: 3
Classifier: Programming Language :: Python :: 3.7
Requires-Dist: numpy
Requires-Dist: pandas
Requires-Dist: matplotlib
Requires-Dist: alpha-vantage
